KubeLibrary/KubeLibrary.py
KubeLibrary/__init__.py
KubeLibrary/exceptions.py
KubeLibrary/version.py
robotframework_kubelibrary-0.8.10.dist-info/licenses/LICENSE
robotframework_kubelibrary-0.8.10.dist-info/METADATA
robotframework_kubelibrary-0.8.10.dist-info/WHEEL
robotframework_kubelibrary-0.8.10.dist-info/top_level.txt
robotframework_kubelibrary-0.8.10.dist-info/RECORD
