Metadata-Version: 2.4
Name: robotframework-kubelibrary
Version: 0.8.10
Summary: Kubernetes library for Robot Framework
Home-page: https://github.com/devopsspiral/KubeLibrary
Author: Michał Wcisło
Author-email: mwcislo999@gmail.com
License: MIT
Keywords: robotframework testing test automation kubernetes
Classifier: Development Status :: 2 - Pre-Alpha
Classifier: Programming Language :: Python :: 3
Classifier: License :: OSI Approved :: MIT License
Classifier: Operating System :: OS Independent
Classifier: Topic :: Software Development :: Testing
Requires-Python: >=3.6
License-File: LICENSE
Requires-Dist: google-auth>=2.5.0
Requires-Dist: kubernetes>=21.7.0
Requires-Dist: robotframework>=3.2.2
Requires-Dist: urllib3-mock>=0.3.3
Dynamic: author
Dynamic: author-email
Dynamic: classifier
Dynamic: description
Dynamic: description-content-type
Dynamic: home-page
Dynamic: keywords
Dynamic: license
Dynamic: license-file
Dynamic: requires-dist
Dynamic: requires-python
Dynamic: summary
